README.md
setup.cfg
setup.py
khleetest1.egg-info/PKG-INFO
khleetest1.egg-info/SOURCES.txt
khleetest1.egg-info/dependency_links.txt
khleetest1.egg-info/not-zip-safe
khleetest1.egg-info/top_level.txt
ssllabtest/__init__.py
ssllabtest/main.py