Metadata-Version: 2.1
Name: khleetest1
Version: 1.0.0
Summary: SSL-Seminar-test repository:: Topic - Package Test and Deployment
Home-page: https://github.com/KeonHeeLee/ssl-lab-test
Author: Keon-Hee Lee
Author-email: beta1360@naver.com
License: MIT
Download-URL: https://github.com/KeonHeeLee/ssl-lab-test/archive/v1.0.0.tar.gz
Keywords: Test,TDD,Deployment,Seminar
Platform: UNKNOWN
Classifier: Programming Language :: Python :: 3
Classifier: Programming Language :: Python :: 3.2
Classifier: Programming Language :: Python :: 3.3
Classifier: Programming Language :: Python :: 3.4
Classifier: Programming Language :: Python :: 3.5
Classifier: Programming Language :: Python :: 3.6
Requires-Python: >=3
